src/reg_file.v
`timescale 1ns/1ps

module regfile(
input clk,we,
input [4:0]rs1,
input [4:0]rs2,
input [4:0] rd,
input [31:0]wd,
output reg[31:0] rd1,
output reg[31:0] rd2
);

reg [31:0] regs [0:31];

assign rd1 = regs[rs1];
assign rd2 = regs[rs2];

always @(posedge clk)
begin
  if(we && rd != 5'b00000)
        regs[rd] <= wd;

    regs[0] <= 32'b0;

end
endmodule

src/test/reg_tb.v
`timescale 1ns/1ps

module regfile_tb;

reg clk;
reg we;

reg  [4:0] rs1;
reg  [4:0] rs2;
reg  [4:0] rd;

reg  [31:0] wd;

wire [31:0] rd1;
wire [31:0] rd2;


// DUT
regfile dut(

    .clk(clk),
    .we(we),

    .rs1(rs1),
    .rs2(rs2),
    .rd(rd),

    .wd(wd),

    .rd1(rd1),
    .rd2(rd2)

);


// Clock Generation
always #5 clk = ~clk;


// Waveform Dump
initial begin
    $dumpfile("regfile.vcd");
    $dumpvars(0, regfile_tb);
end


// Test Cases
initial begin

    clk = 0;

    we  = 0;
    rs1 = 0;
    rs2 = 0;
    rd  = 0;
    wd  = 0;

    #10;

    // WRITE x1 = 100
    we = 1;
    rd = 5'd1;
    wd = 32'd100;

    #10;


    // WRITE x2 = 200
    rd = 5'd2;
    wd = 32'd200;

    #10;


    // READ x1 and x2
    we  = 0;

    rs1 = 5'd1;
    rs2 = 5'd2;

    #10;


    // TRY WRITING x0
    we = 1;
    rd = 5'd0;
    wd = 32'd999;

    #10;


    // READ x0
    we  = 0;
    rs1 = 5'd0;

    #10;


    $finish;

end

endmodule

src/test/regfile.vcd
$version Generated by VerilatedVcd $end
$timescale 1ps $end
 $scope module regfile_tb $end
  $var wire 1 G clk $end
  $var wire 1 " we $end
  $var wire 5 # rs1 [4:0] $end
  $var wire 5 $ rs2 [4:0] $end
  $var wire 5 % rd [4:0] $end
  $var wire 32 & wd [31:0] $end
  $var wire 32 H rd1 [31:0] $end
  $var wire 32 I rd2 [31:0] $end
  $scope module dut $end
   $var wire 1 G clk $end
   $var wire 1 " we $end
   $var wire 5 # rs1 [4:0] $end
   $var wire 5 $ rs2 [4:0] $end
   $var wire 5 % rd [4:0] $end
   $var wire 32 & wd [31:0] $end
   $var wire 32 H rd1 [31:0] $end
   $var wire 32 I rd2 [31:0] $end
   $var wire 32 ' regs[0] [31:0] $end
   $var wire 32 ( regs[1] [31:0] $end
   $var wire 32 ) regs[2] [31:0] $end
   $var wire 32 * regs[3] [31:0] $end
   $var wire 32 + regs[4] [31:0] $end
   $var wire 32 , regs[5] [31:0] $end
   $var wire 32 - regs[6] [31:0] $end
   $var wire 32 . regs[7] [31:0] $end
   $var wire 32 / regs[8] [31:0] $end
   $var wire 32 0 regs[9] [31:0] $end
   $var wire 32 1 regs[10] [31:0] $end
   $var wire 32 2 regs[11] [31:0] $end
   $var wire 32 3 regs[12] [31:0] $end
   $var wire 32 4 regs[13] [31:0] $end
   $var wire 32 5 regs[14] [31:0] $end
   $var wire 32 6 regs[15] [31:0] $end
   $var wire 32 7 regs[16] [31:0] $end
   $var wire 32 8 regs[17] [31:0] $end
   $var wire 32 9 regs[18] [31:0] $end
   $var wire 32 : regs[19] [31:0] $end
   $var wire 32 ; regs[20] [31:0] $end
   $var wire 32 < regs[21] [31:0] $end
   $var wire 32 = regs[22] [31:0] $end
   $var wire 32 > regs[23] [31:0] $end
   $var wire 32 ? regs[24] [31:0] $end
   $var wire 32 @ regs[25] [31:0] $end
   $var wire 32 A regs[26] [31:0] $end
   $var wire 32 B regs[27] [31:0] $end
   $var wire 32 C regs[28] [31:0] $end
   $var wire 32 D regs[29] [31:0] $end
   $var wire 32 E regs[30] [31:0] $end
   $var wire 32 F regs[31] [31:0] $end
  $upscope $end
 $upscope $end
$enddefinitions $end


#0
0"
b00000 #
b00000 $
b00000 %
b00000000000000000000000000000000 &
b00000000000000000000000000000000 '
b00000000000000000000000000000000 (
b00000000000000000000000000000000 )
b00000000000000000000000000000000 *
b00000000000000000000000000000000 +
b00000000000000000000000000000000 ,
b00000000000000000000000000000000 -
b00000000000000000000000000000000 .
b00000000000000000000000000000000 /
b00000000000000000000000000000000 0
b00000000000000000000000000000000 1
b00000000000000000000000000000000 2
b00000000000000000000000000000000 3
b00000000000000000000000000000000 4
b00000000000000000000000000000000 5
b00000000000000000000000000000000 6
b00000000000000000000000000000000 7
b00000000000000000000000000000000 8
b00000000000000000000000000000000 9
b00000000000000000000000000000000 :
b00000000000000000000000000000000 ;
b00000000000000000000000000000000 <
b00000000000000000000000000000000 =
b00000000000000000000000000000000 >
b00000000000000000000000000000000 ?
b00000000000000000000000000000000 @
b00000000000000000000000000000000 A
b00000000000000000000000000000000 B
b00000000000000000000000000000000 C
b00000000000000000000000000000000 D
b00000000000000000000000000000000 E
b00000000000000000000000000000000 F
0G
b00000000000000000000000000000000 H
b00000000000000000000000000000000 I
#5000
1G
#10000
1"
b00001 %
b00000000000000000000000001100100 &
0G
#15000
b00000000000000000000000001100100 (
1G
#20000
b00010 %
b00000000000000000000000011001000 &
0G
#25000
b00000000000000000000000011001000 )
1G
#30000
0"
b00001 #
b00010 $
0G
b00000000000000000000000001100100 H
b00000000000000000000000011001000 I
#35000
1G
#40000
1"
b00000 %
b00000000000000000000001111100111 &
0G
#45000
1G
#50000
0"
b00000 #
0G
b00000000000000000000000000000000 H
